{
"type": "FeatureCollection",
"name": "espacios-verdes",
"crs": { "type": "name", "properties": { "name": "urn:ogc:def:crs:OGC:1.3:CRS84" } },
"features": [
{ "type": "Feature", "properties": { "Esp_Verdes": null }, "geometry": { "type": "Point", "coordinates": [ -65.014200275551133, -32.335123371743506 ] } },
{ "type": "Feature", "properties": { "Esp_Verdes": null }, "geometry": { "type": "Point", "coordinates": [ -65.006716558116253, -32.333448146292604 ] } },
{ "type": "Feature", "properties": { "Esp_Verdes": null }, "geometry": { "type": "Point", "coordinates": [ -65.020572394789596, -32.334763276553126 ] } },
{ "type": "Feature", "properties": { "Esp_Verdes": null }, "geometry": { "type": "Point", "coordinates": [ -65.014904809619281, -32.343695202905835 ] } },
{ "type": "Feature", "properties": { "Esp_Verdes": null }, "geometry": { "type": "Point", "coordinates": [ -65.017816883767566, -32.361872181863745 ] } },
{ "type": "Feature", "properties": { "Esp_Verdes": null }, "geometry": { "type": "Point", "coordinates": [ -65.00494739478961, -32.349942071643298 ] } },
{ "type": "Feature", "properties": { "Esp_Verdes": null }, "geometry": { "type": "Point", "coordinates": [ -65.022654684368774, -32.350482214428872 ] } },
{ "type": "Feature", "properties": { "Esp_Verdes": null }, "geometry": { "type": "Point", "coordinates": [ -64.999091933867788, -32.333643850200424 ] } },
{ "type": "Feature", "properties": { "Esp_Verdes": null }, "geometry": { "type": "Point", "coordinates": [ -64.999107590180415, -32.354623309118267 ] } },
{ "type": "Feature", "properties": { "Esp_Verdes": null }, "geometry": { "type": "Point", "coordinates": [ -64.988007264529088, -32.377528494489013 ] } },
{ "type": "Feature", "properties": { "Esp_Verdes": null }, "geometry": { "type": "Point", "coordinates": [ -65.010035696392833, -32.410211047094215 ] } },
{ "type": "Feature", "properties": { "Esp_Verdes": null }, "geometry": { "type": "Point", "coordinates": [ -65.008423096192459, -32.414923597194417 ] } },
{ "type": "Feature", "properties": { "Esp_Verdes": null }, "geometry": { "type": "Point", "coordinates": [ -64.979255385771609, -32.412293336673372 ] } },
{ "type": "Feature", "properties": { "Esp_Verdes": null }, "geometry": { "type": "Point", "coordinates": [ -65.009722570140326, -32.438572457414864 ] } },
{ "type": "Feature", "properties": { "Esp_Verdes": null }, "geometry": { "type": "Point", "coordinates": [ -65.009299849699474, -32.442290831663364 ] } },
{ "type": "Feature", "properties": { "Esp_Verdes": null }, "geometry": { "type": "Point", "coordinates": [ -65.024768286573192, -32.323944764529088 ] } }
]
}
